BioUtensils/__init__.py
BioUtensils/extraction.py
BioUtensils/normalize.py
BioUtensils/rgb_utils.py
BioUtensils-0.12.dist-info/METADATA
BioUtensils-0.12.dist-info/WHEEL
BioUtensils-0.12.dist-info/top_level.txt
BioUtensils-0.12.dist-info/RECORD
