Metadata-Version: 2.1
Name: BioUtensils
Version: 0.12
Home-page: https://github.com/SimonBon/Bioutensils
Author: Simon Gutwein
Author-email: simon.gutwein@ccri.at
License: MIT
Classifier: License :: OSI Approved :: MIT License
Classifier: Programming Language :: Python
Classifier: Programming Language :: Python :: 3
Classifier: Programming Language :: Python :: 3.9
Requires-Dist: numpy
Requires-Dist: scipy
Requires-Dist: scikit-image
